adafruit_am2320.py
adafruit_circuitpython_am2320-1.2.25.dist-info/licenses/LICENSE
adafruit_circuitpython_am2320-1.2.25.dist-info/METADATA
adafruit_circuitpython_am2320-1.2.25.dist-info/WHEEL
adafruit_circuitpython_am2320-1.2.25.dist-info/top_level.txt
adafruit_circuitpython_am2320-1.2.25.dist-info/RECORD
